pytest_tldr.py
pytest_tldr-0.2.6.dist-info/licenses/LICENSE
pytest_tldr-0.2.6.dist-info/METADATA
pytest_tldr-0.2.6.dist-info/WHEEL
pytest_tldr-0.2.6.dist-info/entry_points.txt
pytest_tldr-0.2.6.dist-info/top_level.txt
pytest_tldr-0.2.6.dist-info/RECORD
