Metadata-Version: 2.4
Name: pytest-tldr
Version: 0.2.6
Summary: A pytest plugin that limits the output to just the things you need.
Author-email: Russell Keith-Magee <russell@keith-magee.com>
Maintainer-email: Russell Keith-Magee <russell@keith-magee.com>
License-Expression: BSD-3-Clause
Project-URL: Funding, https://beeware.org/contributing/membership/
Project-URL: Tracker, https://github.com/freakboy3742/pytest-tldr/issues
Project-URL: Source, https://github.com/freakboy3742/pytest-tldr
Keywords: pytest
Classifier: Development Status :: 4 - Beta
Classifier: Framework :: Pytest
Classifier: Intended Audience :: Developers
Classifier: Topic :: Software Development :: Testing
Classifier: Programming Language :: Python
Classifier: Programming Language :: Python :: 3
Classifier: Programming Language :: Python :: 3.10
Classifier: Programming Language :: Python :: 3.11
Classifier: Programming Language :: Python :: 3.12
Classifier: Programming Language :: Python :: 3.13
Classifier: Programming Language :: Python :: 3.14
Classifier: Programming Language :: Python :: 3.15
Classifier: Programming Language :: Python :: 3 :: Only
Classifier: Programming Language :: Python :: Implementation :: CPython
Classifier: Programming Language :: Python :: Implementation :: PyPy
Classifier: Operating System :: OS Independent
Requires-Python: >=3.10
License-File: LICENSE
Requires-Dist: pytest>=7.0.0
Dynamic: license-file
